{"citation": {"fields": [{"title": "Times Mirror Prelude to the Election, October 1994"}, {"otherId": [{"otherIdValue": "D-30974", "otherIdAgency": "odum"}]}, {"author": [{"authorName": "Princeton Survey Research Associates"}]}, {"datasetContact": [{"datasetContactEmail": "N/A"}]}, {"dsDescription": [{"dsDescriptionValue": "<p>This survey focuses on voting intentions, most important problem facing country, party preference, approval of Clinton on various issues, Contract with America, Christian Coalition, and radio shows.</p>"}]}, {"keyword": [{"keywordVocabulary": "ODUM:INDEX.TERMS", "keywordValue": "Elections"}, {"keywordVocabulary": "ODUM:INDEX.TERMS", "keywordValue": "Voting behavior"}, {"keywordVocabulary": "ODUM:INDEX.TERMS", "keywordValue": "Media coverage"}, {"keywordVocabulary": "ODUM:INDEX.TERMS", "keywordValue": "Radio and television"}]}, {"topicClassification": [{"topicClassValue": "Media and communications", "topicClassVocab": "ODUM:MAIN.HEADING"}]}, {"notesText": "Subject: Study Level Error Note, Notes: Telephone survey among a nationwide sample of 2,052 US adults, 18 years of age and older.; Subject: null  Type: ODUM:ACCESS.CATEGORY  Notes: II;"}, {"producer": [{"producerName": "Princeton Survey Research Associates"}]}, {"productionDate": "1994"}, {"productionPlace": "Princeton, NJ"}, {"distributor": [{"distributorName": "Odum Institute"}, {"distributorName": "The Pew Research Center"}]}, {"distributionDate": "1996"}, {"timePeriodCovered": [{"timePeriodCoveredStart": "1994-10-20", "timePeriodCoveredEnd": "1994-10-24"}]}, {"kindOfData": ["Numeric (Survey)"]}], "displayName": "Citation Metadata"}, "geospatial": {"fields": [{"geographicCoverage": [{"otherGeographicCoverage": "United States"}]}], "displayName": "Geospatial Metadata"}}