{"citation": {"fields": [{"title": "Harris 1993 Wausau Health Care Experiences Survey, study no. 932003"}, {"otherId": [{"otherIdValue": "H-932003", "otherIdAgency": "odum"}, {"otherIdValue": "Harris study no. 932003", "otherIdAgency": "odum:extended"}]}, {"author": [{"authorName": "Louis Harris and Associates, Inc."}]}, {"datasetContact": [{"datasetContactEmail": "N/A"}]}, {"dsDescription": [{"dsDescriptionValue": "<p>This survey focuses on fears, concerns, and experiences of health care consumers and providers in Wausau, Wisconsin. Variables include costs, insurance, health status, access to health care, managed care, reform options, impact of health concerns on respondent's life and employment choices.</p>"}]}, {"keyword": [{"keywordVocabulary": "ODUM:INDEX.TERMS", "keywordValue": "Health care"}, {"keywordVocabulary": "ODUM:INDEX.TERMS", "keywordValue": "Family finances"}, {"keywordVocabulary": "ODUM:INDEX.TERMS", "keywordValue": "Health insurance"}]}, {"topicClassification": [{"topicClassValue": "Omnibus and public opinion", "topicClassVocab": "ODUM:MAIN.HEADING"}, {"topicClassValue": "Health", "topicClassVocab": "ODUM:MAIN.HEADING"}]}, {"notesText": "Subject: Study Level Error Note, Notes: National random digit dialing; Universe: American adults aged 18 years of age and older. An additional sample included Wausau employers representing all industry categories.; Subject: null  Type: ODUM:ACCESS.CATEGORY  Notes: I; Subject: null  Type: ODUM:CODEBOOK.NUMBER  Notes: H-932003;"}, {"producer": [{"producerName": "Louis Harris and Associates, Inc."}]}, {"productionDate": "1993-02"}, {"productionPlace": "New York, NY"}, {"distributor": [{"distributorName": "Odum Institute"}, {"distributorName": "Odum Institute for Research in Social Science"}]}, {"distributionDate": "1995"}, {"dateOfCollection": [{"dateOfCollectionEnd": "1993-03-17", "dateOfCollectionStart": "1993-02-25"}]}, {"kindOfData": ["Numeric (Survey)"]}, {"series": {"seriesName": "Harris public opinion survey"}}], "displayName": "Citation Metadata"}, "geospatial": {"fields": [{"geographicCoverage": [{"otherGeographicCoverage": "United States"}]}], "displayName": "Geospatial Metadata"}}